easytester/__init__.py
easytester/move.py
easytester/utils.py
easytester-0.2.dist-info/METADATA
easytester-0.2.dist-info/WHEEL
easytester-0.2.dist-info/top_level.txt
easytester-0.2.dist-info/RECORD
