Metadata-Version: 2.1
Name: easytester
Version: 0.2
Summary: A simple and easy-to-use testing library for web and mobile applications
Home-page: https://github.com/Hamsterrrrr/EasyTest
Author: hamsterrrrr
Author-email: radzabovibragim80@gmail.com
License: UNKNOWN
Platform: UNKNOWN
Classifier: Programming Language :: Python :: 3
Classifier: License :: OSI Approved :: MIT License
Classifier: Operating System :: OS Independent
Requires-Python: >=3.6
Requires-Dist: allure-pytest
Requires-Dist: appium-python-client
Requires-Dist: selenium
